{
	"users": {
		"designer": {
			"alias": "Designer"
		},
		"administrator": {
			"alias": "Administrator"
		},
		"al": {
			"password": "$2b$10$LgVX8Xx/QKxdaGzl8TfnMuX5lwSnVtEgDap7WaninUktx4NI7AKeG"
		}
	},
	"sqlSchemaGranters": {
		"DEFAULT_SCHEMA": {
			"readOnlyAccessGroup": "*",
			"readWriteAccessGroup": "*",
			"allAccessGroup": ""
		}
	},
	"settings": {
		"localGenericWebUser": "Designer",
		"designAccessGroup": "*",
		"localMobileAccessGroupRW": "*",
		"remoteMobileAccessGroupRW": "*",
		"remoteGenericWebUser": "Designer",
		"remoteDefaultUser": ""
	}
}